cortecs_py/__init__.py
cortecs_py/client.py
cortecs_py/schemas.py
cortecs_py/utils.py
cortecs_py/integrations/__init__.py
cortecs_py/integrations/langchain/__init__.py
cortecs_py/integrations/langchain/dedicated_llm.py
cortecs_py-0.1.2.dist-info/LICENSE
cortecs_py-0.1.2.dist-info/METADATA
cortecs_py-0.1.2.dist-info/WHEEL
cortecs_py-0.1.2.dist-info/top_level.txt
cortecs_py-0.1.2.dist-info/RECORD
