Metadata-Version: 2.2
Name: cortecs-py
Version: 0.1.2
Summary: Lightweight wrapper for cortecs.ai enabling ⚡️ instant provisioning
Author-email: Markus Tretzmüller <markus.tretzmuller@cortecs.ai>, Eva Jagodic <eva.jagodic@cortecs.ai>
Project-URL: Homepage, https://github.com/cortecs-ai/cortecs-py
Project-URL: Docs, https://docs.cortecs.ai/cortecs-py/python-client
Project-URL: Issues, https://github.com/cortecs-ai/cortecs-py/issues
Classifier: Programming Language :: Python :: 3
Classifier: License :: OSI Approved :: MIT License
Requires-Python: >=3.10
License-File: LICENSE
Requires-Dist: requests
Requires-Dist: tqdm
Requires-Dist: pydantic
Requires-Dist: langchain>=0.2.0
Requires-Dist: langchain-openai>=0.1.25
Provides-Extra: crewai-integration
Requires-Dist: crewai>=0.83.0; extra == "crewai-integration"
Provides-Extra: dev
Requires-Dist: python-dotenv; extra == "dev"
Requires-Dist: ruff; extra == "dev"
Requires-Dist: bandit; extra == "dev"
Provides-Extra: examples
Requires-Dist: langchain-community; extra == "examples"
Requires-Dist: arxiv; extra == "examples"
Requires-Dist: pymupdf; extra == "examples"
Requires-Dist: praw; extra == "examples"
Requires-Dist: crewai>=0.83.0; extra == "examples"
Requires-Dist: transformers; extra == "examples"
Provides-Extra: all
Requires-Dist: crewai>=0.83.0; extra == "all"
Requires-Dist: langchain-community; extra == "all"
Requires-Dist: arxiv; extra == "all"
Requires-Dist: pymupdf; extra == "all"
Requires-Dist: praw; extra == "all"
Requires-Dist: transformers; extra == "all"
